tetragono/__init__.py
tetragono/abstract_lattice.py
tetragono/abstract_state.py
tetragono/conversion.py
tetragono/exact_state.py
tetragono/shell.py
tetragono/simple_update_lattice.py
tetragono/tensor_element.py
tetragono/utility.py
tetragono/auxiliaries/__init__.py
tetragono/auxiliaries/double_layer_auxiliaries.py
tetragono/auxiliaries/single_layer_auxiliaries.py
tetragono/auxiliaries/three_line_auxiliaries.py
tetragono/common_tensor/Fermi.py
tetragono/common_tensor/FermiFermi_Hubbard.py
tetragono/common_tensor/FermiU1_Hubbard.py
tetragono/common_tensor/FermiU1_tJ.py
tetragono/common_tensor/Fermi_Hubbard.py
tetragono/common_tensor/No.py
tetragono/common_tensor/Parity.py
tetragono/common_tensor/Parity_Hubbard.py
tetragono/common_tensor/__init__.py
tetragono/common_tensor/tensor_toolkit.py
tetragono/sampling_lattice/__init__.py
tetragono/sampling_lattice/gradient.py
tetragono/sampling_lattice/lattice.py
tetragono/sampling_lattice/observer.py
tetragono/sampling_lattice/sampling.py
tetragono/sampling_lattice/squash/__init__.py
tetragono/sampling_lattice/squash/horizontal.py
tetragono/sampling_lattice/squash/vertical.py
tetragono/sampling_neural_state/__init__.py
tetragono/sampling_neural_state/gradient.py
tetragono/sampling_neural_state/observer.py
tetragono/sampling_neural_state/sampling.py
tetragono/sampling_neural_state/state.py
tetragono-0.3.17.dist-info/METADATA
tetragono-0.3.17.dist-info/WHEEL
tetragono-0.3.17.dist-info/top_level.txt
tetragono-0.3.17.dist-info/RECORD
